finch/__init__.py
finch/_array_api_info.py
finch/compiled.py
finch/dtypes.py
finch/errors.py
finch/io.py
finch/julia.py
finch/juliapkg.json
finch/juliapkg_dev.json
finch/levels.py
finch/linalg/__init__.py
finch/linalg/_linalg.py
finch/tensor.py
finch/typing.py
finch_tensor-0.2.14.dist-info/METADATA
finch_tensor-0.2.14.dist-info/WHEEL
finch_tensor-0.2.14.dist-info/licenses/LICENSE
finch_tensor-0.2.14.dist-info/RECORD
