Metadata-Version: 2.4
Name: finch-tensor
Version: 0.2.14
Summary: Sparse Tensor Programming in Python powered by Finch.jl
License-File: LICENSE
Author: Willow Ahrens
Author-email: willow.marie.ahrens@gmail.com
Requires-Python: >=3.11,<4.0
Classifier: Programming Language :: Python :: 3
Classifier: Programming Language :: Python :: 3.11
Classifier: Programming Language :: Python :: 3.12
Classifier: Programming Language :: Python :: 3.13
Classifier: Programming Language :: Python :: 3.14
Provides-Extra: test
Requires-Dist: juliacall (>=0.9.24,<0.10.0)
Requires-Dist: juliapkg (>=0.1.16,<0.2.0)
Requires-Dist: numba (>=0.61.0) ; extra == "test"
Requires-Dist: numpy (>=1.19)
Requires-Dist: pre-commit (>=3.6.0,<4) ; extra == "test"
Requires-Dist: pytest (>=7.4.4,<8) ; extra == "test"
Requires-Dist: pytest-cov (>=4.1.0,<5) ; extra == "test"
Requires-Dist: scipy (>=1.7,<2) ; extra == "test"
Requires-Dist: sparse (>=0.16.0) ; extra == "test"
